moschitta_auth/__init__.py
moschitta_auth/authorization.py
moschitta_auth/base_authentication.py
moschitta_auth/basic_authenticator.py
moschitta_auth/helper_functions.py
moschitta_auth/logout.py
moschitta_auth-0.1.1.dist-info/LICENSE
moschitta_auth-0.1.1.dist-info/METADATA
moschitta_auth-0.1.1.dist-info/WHEEL
moschitta_auth-0.1.1.dist-info/RECORD
