Metadata-Version: 2.1
Name: moschitta-auth
Version: 0.1.1
Summary: 
Author: Skyler Saville
Author-email: skylersaville@gmail.com
Requires-Python: >=3.11,<4.0
Classifier: Programming Language :: Python :: 3
Classifier: Programming Language :: Python :: 3.11
Requires-Dist: bcrypt (>=4.1.3,<5.0.0)
